cdklabs/cdk_verified_permissions/__init__.py
cdklabs/cdk_verified_permissions/py.typed
cdklabs/cdk_verified_permissions/_jsii/__init__.py
cdklabs/cdk_verified_permissions/_jsii/cdk-verified-permissions@0.3.1.jsii.tgz
cdklabs_cdk_verified_permissions-0.3.1.dist-info/LICENSE
cdklabs_cdk_verified_permissions-0.3.1.dist-info/METADATA
cdklabs_cdk_verified_permissions-0.3.1.dist-info/NOTICE
cdklabs_cdk_verified_permissions-0.3.1.dist-info/WHEEL
cdklabs_cdk_verified_permissions-0.3.1.dist-info/top_level.txt
cdklabs_cdk_verified_permissions-0.3.1.dist-info/RECORD
